pyrbi/__init__.py
pyrbi/exceptions.py
pyrbi/models.py
pyrbi-0.1.0.dist-info/WHEEL
pyrbi-0.1.0.dist-info/METADATA
pyrbi-0.1.0.dist-info/RECORD
