Metadata-Version: 2.1
Name: pyrbi
Version: 0.1.0
Summary: 
Author: Felipe Rodrigues
Author-email: felipe@felipevr.com
Requires-Python: >=3.7,<4.0
Classifier: Programming Language :: Python :: 3
Classifier: Programming Language :: Python :: 3.7
Requires-Dist: requests (>=2.22,<3.0)
